turbodesigner/__init__.py
turbodesigner/exporter.py
turbodesigner/flow_station.py
turbodesigner/stage.py
turbodesigner/turbomachinery.py
turbodesigner/units.py
turbodesigner/visualizer.py
turbodesigner/airfoils/DCA.py
turbodesigner/airfoils/__init__.py
turbodesigner/airfoils/common.py
turbodesigner/attachments/__init__.py
turbodesigner/attachments/firetree.py
turbodesigner/blade/__init__.py
turbodesigner/blade/metal_angles.py
turbodesigner/blade/row.py
turbodesigner/blade/metal_angle_methods/__init__.py
turbodesigner/blade/metal_angle_methods/johnsen_bullock.py
turbodesigner/blade/vortex/__init__.py
turbodesigner/blade/vortex/common.py
turbodesigner/blade/vortex/free_vortex.py
turbodesigner/cad/__init__.py
turbodesigner/cad/blade.py
turbodesigner/cad/casing.py
turbodesigner/cad/common.py
turbodesigner/cad/shaft.py
turbodesigner-1.0.0.dist-info/licenses/LICENSE
turbodesigner-1.0.0.dist-info/METADATA
turbodesigner-1.0.0.dist-info/WHEEL
turbodesigner-1.0.0.dist-info/top_level.txt
turbodesigner-1.0.0.dist-info/RECORD
