Metadata-Version: 2.4
Name: turbodesigner
Version: 1.0.0
Summary: An open-source turbomachinery designer
Home-page: https://github.com/OpenOrion/turbodesigner
Author: Open Orion, Inc.
Classifier: Programming Language :: Python :: 3
Classifier: License :: OSI Approved :: MIT License
Classifier: Operating System :: OS Independent
Classifier: Topic :: Scientific/Engineering :: Physics
Classifier: Topic :: Scientific/Engineering :: Visualization
Requires-Python: >=3.8
License-File: LICENSE
Requires-Dist: kaleido
Requires-Dist: plotly==5.11.0
Requires-Dist: ipywidgets>=7.6
Requires-Dist: jupyterlab
Requires-Dist: matplotlib
Requires-Dist: numpy
Requires-Dist: dacite
Requires-Dist: pandas
Requires-Dist: cadquery
Dynamic: author
Dynamic: classifier
Dynamic: description
Dynamic: description-content-type
Dynamic: home-page
Dynamic: license-file
Dynamic: requires-dist
Dynamic: requires-python
Dynamic: summary
